periodic/__init__.py
periodic/periodic.py
asyncio_periodic-2019.2.dist-info/LICENSE
asyncio_periodic-2019.2.dist-info/METADATA
asyncio_periodic-2019.2.dist-info/WHEEL
asyncio_periodic-2019.2.dist-info/top_level.txt
asyncio_periodic-2019.2.dist-info/RECORD
